nyan/__init__.py
nyan/circle.py
nyan/color.py
nyan/custom_event.py
nyan/game.py
nyan/image_sprite.py
nyan/keyboard.py
nyan/mouse.py
nyan/music.py
nyan/nyan_packager.py
nyan/random.py
nyan/rect.py
nyan/screen.py
nyan/sound.py
nyan/sprite.py
nyan/sprite_manager.py
nyan/task_runner.py
nyan/text.py
nyan/timer.py
nyan/utils.py
nyan-0.14.1.dist-info/METADATA
nyan-0.14.1.dist-info/WHEEL
nyan-0.14.1.dist-info/entry_points.txt
nyan-0.14.1.dist-info/licenses/LICENSE
nyan-0.14.1.dist-info/RECORD
