Metadata-Version: 2.4
Name: nyan
Version: 0.14.1
Summary: The easiest way to start coding games and graphics projects in Python
Author-email: ducaale <sharaf.13@hotmail.com>
License-Expression: MIT
License-File: LICENSE
Requires-Python: >=3.9
Requires-Dist: pygame>=2.6.1
Requires-Dist: pyinstaller>=6.13
